ament_cmake_pytest/_dummy.cpython-310-x86_64-linux-gnu.so
ros_ament_cmake_pytest-2.7.3.data/data/share/ament_cmake_pytest/local_setup.bash
ros_ament_cmake_pytest-2.7.3.data/data/share/ament_cmake_pytest/local_setup.dsv
ros_ament_cmake_pytest-2.7.3.data/data/share/ament_cmake_pytest/local_setup.sh
ros_ament_cmake_pytest-2.7.3.data/data/share/ament_cmake_pytest/local_setup.zsh
ros_ament_cmake_pytest-2.7.3.data/data/share/ament_cmake_pytest/package.dsv
ros_ament_cmake_pytest-2.7.3.data/data/share/ament_cmake_pytest/package.xml
ros_ament_cmake_pytest-2.7.3.data/data/share/ament_cmake_pytest/cmake/ament_add_pytest_test.cmake
ros_ament_cmake_pytest-2.7.3.data/data/share/ament_cmake_pytest/cmake/ament_cmake_pytest-extras.cmake
ros_ament_cmake_pytest-2.7.3.data/data/share/ament_cmake_pytest/cmake/ament_cmake_pytestConfig-version.cmake
ros_ament_cmake_pytest-2.7.3.data/data/share/ament_cmake_pytest/cmake/ament_cmake_pytestConfig.cmake
ros_ament_cmake_pytest-2.7.3.data/data/share/ament_cmake_pytest/cmake/ament_get_pytest_cov_version.cmake
ros_ament_cmake_pytest-2.7.3.data/data/share/ament_cmake_pytest/cmake/ament_has_pytest.cmake
ros_ament_cmake_pytest-2.7.3.data/data/share/ament_cmake_pytest/environment/ament_prefix_path.dsv
ros_ament_cmake_pytest-2.7.3.data/data/share/ament_cmake_pytest/environment/ament_prefix_path.sh
ros_ament_cmake_pytest-2.7.3.data/data/share/ament_cmake_pytest/environment/path.dsv
ros_ament_cmake_pytest-2.7.3.data/data/share/ament_cmake_pytest/environment/path.sh
ros_ament_cmake_pytest-2.7.3.data/data/share/ament_index/resource_index/package_run_dependencies/ament_cmake_pytest
ros_ament_cmake_pytest-2.7.3.data/data/share/ament_index/resource_index/packages/ament_cmake_pytest
ros_ament_cmake_pytest-2.7.3.data/data/share/ament_index/resource_index/parent_prefix_path/ament_cmake_pytest
ros_ament_cmake_pytest-2.7.3.dist-info/METADATA
ros_ament_cmake_pytest-2.7.3.dist-info/WHEEL
ros_ament_cmake_pytest-2.7.3.dist-info/top_level.txt
ros_ament_cmake_pytest-2.7.3.dist-info/RECORD
