Metadata-Version: 2.4
Name: ros-ament-cmake-pytest
Version: 2.7.3
Summary: Wheel for the ament_cmake_pytest (ros-ament-cmake-pytest) ROS 2 package.
Dynamic: description
Dynamic: description-content-type
Dynamic: summary
